[
    {
        "id": 1,
        "name": "User 1",
        "email": "user1@example.com",
        "password_hash": "hash1",
        "role_id": 1,
        "profile_picture": "user1.jpg",
        "created_at": "2024-06-10T03:23:23",
        "updated_at": "2025-01-25T22:40:53"
    },
    {
        "id": 2,
        "name": "User 2",
        "email": "user2@example.com",
        "password_hash": "hash2",
        "role_id": 1,
        "profile_picture": "user2.jpg",
        "created_at": "2023-05-09T16:02:38",
        "updated_at": "2024-09-20T18:16:27"
    },
    {
        "id": 3,
        "name": "User 3",
        "email": "user3@example.com",
        "password_hash": "hash3",
        "role_id": 1,
        "profile_picture": "user3.jpg",
        "created_at": "2023-01-16T19:43:08",
        "updated_at": "2024-09-16T14:15:17"
    },
    {
        "id": 4,
        "name": "User 4",
        "email": "user4@example.com",
        "password_hash": "hash4",
        "role_id": 1,
        "profile_picture": "user4.jpg",
        "created_at": "2023-10-30T18:57:53",
        "updated_at": "2025-02-16T01:57:29"
    },
    {
        "id": 5,
        "name": "User 5",
        "email": "user5@example.com",
        "password_hash": "hash5",
        "role_id": 1,
        "profile_picture": "user5.jpg",
        "created_at": "2024-02-05T09:44:06",
        "updated_at": "2023-12-06T07:09:15"
    },
    {
        "id": 6,
        "name": "User 6",
        "email": "user6@example.com",
        "password_hash": "hash6",
        "role_id": 2,
        "profile_picture": "user6.jpg",
        "created_at": "2024-11-27T09:29:11",
        "updated_at": "2023-05-28T23:05:42"
    },
    {
        "id": 7,
        "name": "User 7",
        "email": "user7@example.com",
        "password_hash": "hash7",
        "role_id": 2,
        "profile_picture": "user7.jpg",
        "created_at": "2024-06-20T01:09:10",
        "updated_at": "2023-03-08T04:26:21"
    },
    {
        "id": 8,
        "name": "User 8",
        "email": "user8@example.com",
        "password_hash": "hash8",
        "role_id": 2,
        "profile_picture": "user8.jpg",
        "created_at": "2023-05-29T00:12:57",
        "updated_at": "2023-02-21T06:29:57"
    },
    {
        "id": 9,
        "name": "User 9",
        "email": "user9@example.com",
        "password_hash": "hash9",
        "role_id": 2,
        "profile_picture": "user9.jpg",
        "created_at": "2023-01-11T03:56:32",
        "updated_at": "2024-04-03T01:21:54"
    },
    {
        "id": 10,
        "name": "User 10",
        "email": "user10@example.com",
        "password_hash": "hash10",
        "role_id": 2,
        "profile_picture": "user10.jpg",
        "created_at": "2023-07-18T18:07:50",
        "updated_at": "2024-03-23T04:04:50"
    },
    {
        "id": 11,
        "name": "User 11",
        "email": "user11@example.com",
        "password_hash": "hash11",
        "role_id": 2,
        "profile_picture": "user11.jpg",
        "created_at": "2023-12-21T14:13:33",
        "updated_at": "2024-09-20T15:53:54"
    },
    {
        "id": 12,
        "name": "User 12",
        "email": "user12@example.com",
        "password_hash": "hash12",
        "role_id": 2,
        "profile_picture": "user12.jpg",
        "created_at": "2023-08-09T12:16:21",
        "updated_at": "2023-09-15T20:45:11"
    },
    {
        "id": 13,
        "name": "User 13",
        "email": "user13@example.com",
        "password_hash": "hash13",
        "role_id": 2,
        "profile_picture": "user13.jpg",
        "created_at": "2024-11-12T05:24:09",
        "updated_at": "2024-09-01T14:40:52"
    },
    {
        "id": 14,
        "name": "User 14",
        "email": "user14@example.com",
        "password_hash": "hash14",
        "role_id": 2,
        "profile_picture": "user14.jpg",
        "created_at": "2024-01-13T19:40:46",
        "updated_at": "2024-07-16T11:11:28"
    },
    {
        "id": 15,
        "name": "User 15",
        "email": "user15@example.com",
        "password_hash": "hash15",
        "role_id": 2,
        "profile_picture": "user15.jpg",
        "created_at": "2024-06-12T23:36:07",
        "updated_at": "2023-01-21T04:02:11"
    },
    {
        "id": 16,
        "name": "User 16",
        "email": "user16@example.com",
        "password_hash": "hash16",
        "role_id": 2,
        "profile_picture": "user16.jpg",
        "created_at": "2023-05-28T18:08:58",
        "updated_at": "2023-04-27T01:13:20"
    },
    {
        "id": 17,
        "name": "User 17",
        "email": "user17@example.com",
        "password_hash": "hash17",
        "role_id": 2,
        "profile_picture": "user17.jpg",
        "created_at": "2024-01-11T21:53:06",
        "updated_at": "2025-01-19T06:42:17"
    },
    {
        "id": 18,
        "name": "User 18",
        "email": "user18@example.com",
        "password_hash": "hash18",
        "role_id": 2,
        "profile_picture": "user18.jpg",
        "created_at": "2023-09-29T20:02:17",
        "updated_at": "2023-09-08T18:56:37"
    },
    {
        "id": 19,
        "name": "User 19",
        "email": "user19@example.com",
        "password_hash": "hash19",
        "role_id": 2,
        "profile_picture": "user19.jpg",
        "created_at": "2024-10-10T09:31:12",
        "updated_at": "2023-09-14T13:42:04"
    },
    {
        "id": 20,
        "name": "User 20",
        "email": "user20@example.com",
        "password_hash": "hash20",
        "role_id": 2,
        "profile_picture": "user20.jpg",
        "created_at": "2025-01-14T12:21:46",
        "updated_at": "2023-11-03T08:29:40"
    },
    {
        "id": 21,
        "name": "User 21",
        "email": "user21@example.com",
        "password_hash": "hash21",
        "role_id": 2,
        "profile_picture": "user21.jpg",
        "created_at": "2024-03-04T10:57:36",
        "updated_at": "2023-10-17T06:12:51"
    },
    {
        "id": 22,
        "name": "User 22",
        "email": "user22@example.com",
        "password_hash": "hash22",
        "role_id": 2,
        "profile_picture": "user22.jpg",
        "created_at": "2024-01-18T06:45:05",
        "updated_at": "2023-02-26T21:18:09"
    },
    {
        "id": 23,
        "name": "User 23",
        "email": "user23@example.com",
        "password_hash": "hash23",
        "role_id": 2,
        "profile_picture": "user23.jpg",
        "created_at": "2024-08-11T21:34:21",
        "updated_at": "2025-01-26T23:59:03"
    },
    {
        "id": 24,
        "name": "User 24",
        "email": "user24@example.com",
        "password_hash": "hash24",
        "role_id": 2,
        "profile_picture": "user24.jpg",
        "created_at": "2024-11-12T07:30:13",
        "updated_at": "2023-08-02T20:51:02"
    },
    {
        "id": 25,
        "name": "User 25",
        "email": "user25@example.com",
        "password_hash": "hash25",
        "role_id": 2,
        "profile_picture": "user25.jpg",
        "created_at": "2023-12-14T12:29:50",
        "updated_at": "2025-01-28T20:32:34"
    },
    {
        "id": 26,
        "name": "User 26",
        "email": "user26@example.com",
        "password_hash": "hash26",
        "role_id": 2,
        "profile_picture": "user26.jpg",
        "created_at": "2023-01-07T22:56:25",
        "updated_at": "2024-07-12T19:35:29"
    },
    {
        "id": 27,
        "name": "User 27",
        "email": "user27@example.com",
        "password_hash": "hash27",
        "role_id": 2,
        "profile_picture": "user27.jpg",
        "created_at": "2024-01-24T13:51:59",
        "updated_at": "2024-09-22T01:06:42"
    },
    {
        "id": 28,
        "name": "User 28",
        "email": "user28@example.com",
        "password_hash": "hash28",
        "role_id": 2,
        "profile_picture": "user28.jpg",
        "created_at": "2024-01-15T20:38:40",
        "updated_at": "2023-09-28T16:22:40"
    },
    {
        "id": 29,
        "name": "User 29",
        "email": "user29@example.com",
        "password_hash": "hash29",
        "role_id": 2,
        "profile_picture": "user29.jpg",
        "created_at": "2024-01-08T18:57:11",
        "updated_at": "2024-01-03T09:52:06"
    },
    {
        "id": 30,
        "name": "User 30",
        "email": "user30@example.com",
        "password_hash": "hash30",
        "role_id": 2,
        "profile_picture": "user30.jpg",
        "created_at": "2024-04-23T07:15:24",
        "updated_at": "2024-03-11T06:21:55"
    },
    {
        "id": 31,
        "name": "User 31",
        "email": "user31@example.com",
        "password_hash": "hash31",
        "role_id": 2,
        "profile_picture": "user31.jpg",
        "created_at": "2024-06-21T19:27:13",
        "updated_at": "2023-10-15T01:10:26"
    },
    {
        "id": 32,
        "name": "User 32",
        "email": "user32@example.com",
        "password_hash": "hash32",
        "role_id": 2,
        "profile_picture": "user32.jpg",
        "created_at": "2024-07-05T01:32:47",
        "updated_at": "2025-01-01T20:10:55"
    },
    {
        "id": 33,
        "name": "User 33",
        "email": "user33@example.com",
        "password_hash": "hash33",
        "role_id": 2,
        "profile_picture": "user33.jpg",
        "created_at": "2023-06-24T22:40:22",
        "updated_at": "2024-08-02T11:25:03"
    },
    {
        "id": 34,
        "name": "User 34",
        "email": "user34@example.com",
        "password_hash": "hash34",
        "role_id": 2,
        "profile_picture": "user34.jpg",
        "created_at": "2024-04-20T08:42:00",
        "updated_at": "2025-02-23T23:37:39"
    },
    {
        "id": 35,
        "name": "User 35",
        "email": "user35@example.com",
        "password_hash": "hash35",
        "role_id": 2,
        "profile_picture": "user35.jpg",
        "created_at": "2023-12-09T21:34:39",
        "updated_at": "2023-01-07T03:22:06"
    },
    {
        "id": 36,
        "name": "User 36",
        "email": "user36@example.com",
        "password_hash": "hash36",
        "role_id": 2,
        "profile_picture": "user36.jpg",
        "created_at": "2023-04-18T04:41:34",
        "updated_at": "2025-02-04T09:38:41"
    },
    {
        "id": 37,
        "name": "User 37",
        "email": "user37@example.com",
        "password_hash": "hash37",
        "role_id": 2,
        "profile_picture": "user37.jpg",
        "created_at": "2025-01-04T17:28:42",
        "updated_at": "2024-12-01T04:26:52"
    },
    {
        "id": 38,
        "name": "User 38",
        "email": "user38@example.com",
        "password_hash": "hash38",
        "role_id": 2,
        "profile_picture": "user38.jpg",
        "created_at": "2025-02-23T23:54:27",
        "updated_at": "2024-12-08T02:56:17"
    },
    {
        "id": 39,
        "name": "User 39",
        "email": "user39@example.com",
        "password_hash": "hash39",
        "role_id": 2,
        "profile_picture": "user39.jpg",
        "created_at": "2024-04-21T02:26:33",
        "updated_at": "2024-09-21T15:11:44"
    },
    {
        "id": 40,
        "name": "User 40",
        "email": "user40@example.com",
        "password_hash": "hash40",
        "role_id": 2,
        "profile_picture": "user40.jpg",
        "created_at": "2025-02-19T07:18:09",
        "updated_at": "2023-01-14T05:54:40"
    },
    {
        "id": 41,
        "name": "User 41",
        "email": "user41@example.com",
        "password_hash": "hash41",
        "role_id": 2,
        "profile_picture": "user41.jpg",
        "created_at": "2023-11-16T22:56:07",
        "updated_at": "2024-10-26T19:46:46"
    },
    {
        "id": 42,
        "name": "User 42",
        "email": "user42@example.com",
        "password_hash": "hash42",
        "role_id": 2,
        "profile_picture": "user42.jpg",
        "created_at": "2024-09-19T22:07:34",
        "updated_at": "2024-09-24T16:13:43"
    },
    {
        "id": 43,
        "name": "User 43",
        "email": "user43@example.com",
        "password_hash": "hash43",
        "role_id": 2,
        "profile_picture": "user43.jpg",
        "created_at": "2023-02-27T12:36:29",
        "updated_at": "2023-04-06T19:52:54"
    },
    {
        "id": 44,
        "name": "User 44",
        "email": "user44@example.com",
        "password_hash": "hash44",
        "role_id": 2,
        "profile_picture": "user44.jpg",
        "created_at": "2023-11-16T07:26:48",
        "updated_at": "2023-06-04T10:18:12"
    },
    {
        "id": 45,
        "name": "User 45",
        "email": "user45@example.com",
        "password_hash": "hash45",
        "role_id": 2,
        "profile_picture": "user45.jpg",
        "created_at": "2024-07-11T06:57:55",
        "updated_at": "2023-08-11T10:49:03"
    },
    {
        "id": 46,
        "name": "User 46",
        "email": "user46@example.com",
        "password_hash": "hash46",
        "role_id": 2,
        "profile_picture": "user46.jpg",
        "created_at": "2024-12-06T10:24:19",
        "updated_at": "2023-03-31T04:21:08"
    },
    {
        "id": 47,
        "name": "User 47",
        "email": "user47@example.com",
        "password_hash": "hash47",
        "role_id": 2,
        "profile_picture": "user47.jpg",
        "created_at": "2024-12-09T06:40:10",
        "updated_at": "2023-04-07T10:11:18"
    },
    {
        "id": 48,
        "name": "User 48",
        "email": "user48@example.com",
        "password_hash": "hash48",
        "role_id": 2,
        "profile_picture": "user48.jpg",
        "created_at": "2024-12-26T01:15:40",
        "updated_at": "2023-07-14T00:10:01"
    },
    {
        "id": 49,
        "name": "User 49",
        "email": "user49@example.com",
        "password_hash": "hash49",
        "role_id": 2,
        "profile_picture": "user49.jpg",
        "created_at": "2023-09-21T08:09:42",
        "updated_at": "2024-12-10T05:34:01"
    },
    {
        "id": 50,
        "name": "User 50",
        "email": "user50@example.com",
        "password_hash": "hash50",
        "role_id": 2,
        "profile_picture": "user50.jpg",
        "created_at": "2025-02-13T10:32:04",
        "updated_at": "2024-12-10T02:51:06"
    },
    {
        "id": 51,
        "name": "User 51",
        "email": "user51@example.com",
        "password_hash": "hash51",
        "role_id": 2,
        "profile_picture": "user51.jpg",
        "created_at": "2024-05-31T06:52:31",
        "updated_at": "2024-07-08T01:22:47"
    },
    {
        "id": 52,
        "name": "User 52",
        "email": "user52@example.com",
        "password_hash": "hash52",
        "role_id": 2,
        "profile_picture": "user52.jpg",
        "created_at": "2023-10-21T12:16:29",
        "updated_at": "2024-02-13T19:36:08"
    },
    {
        "id": 53,
        "name": "User 53",
        "email": "user53@example.com",
        "password_hash": "hash53",
        "role_id": 2,
        "profile_picture": "user53.jpg",
        "created_at": "2023-10-06T19:53:34",
        "updated_at": "2024-02-17T21:32:07"
    },
    {
        "id": 54,
        "name": "User 54",
        "email": "user54@example.com",
        "password_hash": "hash54",
        "role_id": 2,
        "profile_picture": "user54.jpg",
        "created_at": "2024-04-24T14:13:55",
        "updated_at": "2024-02-25T08:38:52"
    },
    {
        "id": 55,
        "name": "User 55",
        "email": "user55@example.com",
        "password_hash": "hash55",
        "role_id": 2,
        "profile_picture": "user55.jpg",
        "created_at": "2023-12-01T17:38:19",
        "updated_at": "2024-09-28T09:43:11"
    },
    {
        "id": 56,
        "name": "User 56",
        "email": "user56@example.com",
        "password_hash": "hash56",
        "role_id": 2,
        "profile_picture": "user56.jpg",
        "created_at": "2024-08-21T10:45:52",
        "updated_at": "2023-02-06T08:49:06"
    },
    {
        "id": 57,
        "name": "User 57",
        "email": "user57@example.com",
        "password_hash": "hash57",
        "role_id": 2,
        "profile_picture": "user57.jpg",
        "created_at": "2023-07-19T08:47:15",
        "updated_at": "2024-06-26T10:19:02"
    },
    {
        "id": 58,
        "name": "User 58",
        "email": "user58@example.com",
        "password_hash": "hash58",
        "role_id": 2,
        "profile_picture": "user58.jpg",
        "created_at": "2023-04-13T06:27:45",
        "updated_at": "2024-09-24T02:44:37"
    },
    {
        "id": 59,
        "name": "User 59",
        "email": "user59@example.com",
        "password_hash": "hash59",
        "role_id": 2,
        "profile_picture": "user59.jpg",
        "created_at": "2023-07-06T03:50:22",
        "updated_at": "2023-04-07T18:32:28"
    },
    {
        "id": 60,
        "name": "User 60",
        "email": "user60@example.com",
        "password_hash": "hash60",
        "role_id": 2,
        "profile_picture": "user60.jpg",
        "created_at": "2023-02-15T19:32:14",
        "updated_at": "2023-03-29T09:18:21"
    },
    {
        "id": 61,
        "name": "User 61",
        "email": "user61@example.com",
        "password_hash": "hash61",
        "role_id": 2,
        "profile_picture": "user61.jpg",
        "created_at": "2023-12-21T11:18:33",
        "updated_at": "2023-03-28T02:03:28"
    },
    {
        "id": 62,
        "name": "User 62",
        "email": "user62@example.com",
        "password_hash": "hash62",
        "role_id": 2,
        "profile_picture": "user62.jpg",
        "created_at": "2024-12-19T01:01:43",
        "updated_at": "2023-06-17T20:23:20"
    },
    {
        "id": 63,
        "name": "User 63",
        "email": "user63@example.com",
        "password_hash": "hash63",
        "role_id": 2,
        "profile_picture": "user63.jpg",
        "created_at": "2023-07-29T06:34:59",
        "updated_at": "2024-11-09T11:40:15"
    },
    {
        "id": 64,
        "name": "User 64",
        "email": "user64@example.com",
        "password_hash": "hash64",
        "role_id": 2,
        "profile_picture": "user64.jpg",
        "created_at": "2024-01-14T20:51:15",
        "updated_at": "2024-04-24T02:51:46"
    },
    {
        "id": 65,
        "name": "User 65",
        "email": "user65@example.com",
        "password_hash": "hash65",
        "role_id": 2,
        "profile_picture": "user65.jpg",
        "created_at": "2024-07-30T16:04:04",
        "updated_at": "2024-11-20T19:36:34"
    },
    {
        "id": 66,
        "name": "User 66",
        "email": "user66@example.com",
        "password_hash": "hash66",
        "role_id": 2,
        "profile_picture": "user66.jpg",
        "created_at": "2024-03-05T20:15:56",
        "updated_at": "2025-01-07T01:11:10"
    },
    {
        "id": 67,
        "name": "User 67",
        "email": "user67@example.com",
        "password_hash": "hash67",
        "role_id": 2,
        "profile_picture": "user67.jpg",
        "created_at": "2023-08-27T07:41:07",
        "updated_at": "2023-10-14T18:19:49"
    },
    {
        "id": 68,
        "name": "User 68",
        "email": "user68@example.com",
        "password_hash": "hash68",
        "role_id": 2,
        "profile_picture": "user68.jpg",
        "created_at": "2024-06-05T18:23:37",
        "updated_at": "2025-01-03T12:45:09"
    },
    {
        "id": 69,
        "name": "User 69",
        "email": "user69@example.com",
        "password_hash": "hash69",
        "role_id": 2,
        "profile_picture": "user69.jpg",
        "created_at": "2023-09-19T19:33:01",
        "updated_at": "2024-10-14T09:13:56"
    },
    {
        "id": 70,
        "name": "User 70",
        "email": "user70@example.com",
        "password_hash": "hash70",
        "role_id": 2,
        "profile_picture": "user70.jpg",
        "created_at": "2024-04-01T23:46:28",
        "updated_at": "2023-03-08T10:01:50"
    },
    {
        "id": 71,
        "name": "User 71",
        "email": "user71@example.com",
        "password_hash": "hash71",
        "role_id": 2,
        "profile_picture": "user71.jpg",
        "created_at": "2023-05-03T09:10:47",
        "updated_at": "2025-01-01T07:13:00"
    },
    {
        "id": 72,
        "name": "User 72",
        "email": "user72@example.com",
        "password_hash": "hash72",
        "role_id": 2,
        "profile_picture": "user72.jpg",
        "created_at": "2023-08-06T03:23:52",
        "updated_at": "2024-04-26T12:10:44"
    },
    {
        "id": 73,
        "name": "User 73",
        "email": "user73@example.com",
        "password_hash": "hash73",
        "role_id": 2,
        "profile_picture": "user73.jpg",
        "created_at": "2023-10-05T11:22:20",
        "updated_at": "2024-09-02T07:11:39"
    },
    {
        "id": 74,
        "name": "User 74",
        "email": "user74@example.com",
        "password_hash": "hash74",
        "role_id": 2,
        "profile_picture": "user74.jpg",
        "created_at": "2023-01-06T05:28:16",
        "updated_at": "2024-08-24T06:23:30"
    },
    {
        "id": 75,
        "name": "User 75",
        "email": "user75@example.com",
        "password_hash": "hash75",
        "role_id": 2,
        "profile_picture": "user75.jpg",
        "created_at": "2023-12-27T18:46:48",
        "updated_at": "2024-08-09T06:59:28"
    },
    {
        "id": 76,
        "name": "User 76",
        "email": "user76@example.com",
        "password_hash": "hash76",
        "role_id": 2,
        "profile_picture": "user76.jpg",
        "created_at": "2023-11-01T04:52:56",
        "updated_at": "2023-06-28T06:12:09"
    },
    {
        "id": 77,
        "name": "User 77",
        "email": "user77@example.com",
        "password_hash": "hash77",
        "role_id": 2,
        "profile_picture": "user77.jpg",
        "created_at": "2024-06-18T11:07:38",
        "updated_at": "2023-05-28T16:19:41"
    },
    {
        "id": 78,
        "name": "User 78",
        "email": "user78@example.com",
        "password_hash": "hash78",
        "role_id": 2,
        "profile_picture": "user78.jpg",
        "created_at": "2025-02-03T01:39:29",
        "updated_at": "2025-01-14T23:34:05"
    },
    {
        "id": 79,
        "name": "User 79",
        "email": "user79@example.com",
        "password_hash": "hash79",
        "role_id": 2,
        "profile_picture": "user79.jpg",
        "created_at": "2023-09-29T23:10:54",
        "updated_at": "2024-05-02T00:31:54"
    },
    {
        "id": 80,
        "name": "User 80",
        "email": "user80@example.com",
        "password_hash": "hash80",
        "role_id": 2,
        "profile_picture": "user80.jpg",
        "created_at": "2023-11-18T21:40:41",
        "updated_at": "2023-02-15T00:55:15"
    },
    {
        "id": 81,
        "name": "User 81",
        "email": "user81@example.com",
        "password_hash": "hash81",
        "role_id": 2,
        "profile_picture": "user81.jpg",
        "created_at": "2024-08-12T16:54:49",
        "updated_at": "2023-12-16T15:50:00"
    },
    {
        "id": 82,
        "name": "User 82",
        "email": "user82@example.com",
        "password_hash": "hash82",
        "role_id": 2,
        "profile_picture": "user82.jpg",
        "created_at": "2023-08-07T07:34:45",
        "updated_at": "2023-02-23T11:39:29"
    },
    {
        "id": 83,
        "name": "User 83",
        "email": "user83@example.com",
        "password_hash": "hash83",
        "role_id": 2,
        "profile_picture": "user83.jpg",
        "created_at": "2023-01-21T23:12:26",
        "updated_at": "2024-04-14T14:06:13"
    },
    {
        "id": 84,
        "name": "User 84",
        "email": "user84@example.com",
        "password_hash": "hash84",
        "role_id": 2,
        "profile_picture": "user84.jpg",
        "created_at": "2023-03-23T20:30:59",
        "updated_at": "2025-02-10T03:54:39"
    },
    {
        "id": 85,
        "name": "User 85",
        "email": "user85@example.com",
        "password_hash": "hash85",
        "role_id": 2,
        "profile_picture": "user85.jpg",
        "created_at": "2023-12-26T16:18:09",
        "updated_at": "2023-03-23T22:39:38"
    },
    {
        "id": 86,
        "name": "User 86",
        "email": "user86@example.com",
        "password_hash": "hash86",
        "role_id": 2,
        "profile_picture": "user86.jpg",
        "created_at": "2024-02-18T06:40:46",
        "updated_at": "2023-01-20T15:11:49"
    },
    {
        "id": 87,
        "name": "User 87",
        "email": "user87@example.com",
        "password_hash": "hash87",
        "role_id": 2,
        "profile_picture": "user87.jpg",
        "created_at": "2024-03-10T12:09:00",
        "updated_at": "2024-11-02T16:56:33"
    },
    {
        "id": 88,
        "name": "User 88",
        "email": "user88@example.com",
        "password_hash": "hash88",
        "role_id": 2,
        "profile_picture": "user88.jpg",
        "created_at": "2023-08-30T05:53:33",
        "updated_at": "2024-06-20T09:34:00"
    },
    {
        "id": 89,
        "name": "User 89",
        "email": "user89@example.com",
        "password_hash": "hash89",
        "role_id": 2,
        "profile_picture": "user89.jpg",
        "created_at": "2024-01-10T19:45:32",
        "updated_at": "2023-04-28T14:32:27"
    },
    {
        "id": 90,
        "name": "User 90",
        "email": "user90@example.com",
        "password_hash": "hash90",
        "role_id": 2,
        "profile_picture": "user90.jpg",
        "created_at": "2023-02-11T23:40:15",
        "updated_at": "2024-02-10T01:42:21"
    },
    {
        "id": 91,
        "name": "User 91",
        "email": "user91@example.com",
        "password_hash": "hash91",
        "role_id": 2,
        "profile_picture": "user91.jpg",
        "created_at": "2023-09-09T21:12:43",
        "updated_at": "2024-11-04T01:11:44"
    },
    {
        "id": 92,
        "name": "User 92",
        "email": "user92@example.com",
        "password_hash": "hash92",
        "role_id": 2,
        "profile_picture": "user92.jpg",
        "created_at": "2024-03-19T04:16:11",
        "updated_at": "2023-05-08T11:38:57"
    },
    {
        "id": 93,
        "name": "User 93",
        "email": "user93@example.com",
        "password_hash": "hash93",
        "role_id": 2,
        "profile_picture": "user93.jpg",
        "created_at": "2023-05-18T05:22:37",
        "updated_at": "2024-11-12T11:18:40"
    },
    {
        "id": 94,
        "name": "User 94",
        "email": "user94@example.com",
        "password_hash": "hash94",
        "role_id": 2,
        "profile_picture": "user94.jpg",
        "created_at": "2024-04-28T04:03:07",
        "updated_at": "2023-01-21T05:48:43"
    },
    {
        "id": 95,
        "name": "User 95",
        "email": "user95@example.com",
        "password_hash": "hash95",
        "role_id": 2,
        "profile_picture": "user95.jpg",
        "created_at": "2023-10-19T02:36:44",
        "updated_at": "2023-09-03T08:40:10"
    },
    {
        "id": 96,
        "name": "User 96",
        "email": "user96@example.com",
        "password_hash": "hash96",
        "role_id": 2,
        "profile_picture": "user96.jpg",
        "created_at": "2023-04-02T08:29:22",
        "updated_at": "2023-11-27T07:22:44"
    },
    {
        "id": 97,
        "name": "User 97",
        "email": "user97@example.com",
        "password_hash": "hash97",
        "role_id": 2,
        "profile_picture": "user97.jpg",
        "created_at": "2023-04-21T08:41:16",
        "updated_at": "2023-11-11T07:55:11"
    },
    {
        "id": 98,
        "name": "User 98",
        "email": "user98@example.com",
        "password_hash": "hash98",
        "role_id": 2,
        "profile_picture": "user98.jpg",
        "created_at": "2023-08-04T18:21:40",
        "updated_at": "2023-06-17T02:18:29"
    },
    {
        "id": 99,
        "name": "User 99",
        "email": "user99@example.com",
        "password_hash": "hash99",
        "role_id": 2,
        "profile_picture": "user99.jpg",
        "created_at": "2024-05-02T18:40:18",
        "updated_at": "2023-02-21T11:07:43"
    },
    {
        "id": 100,
        "name": "User 100",
        "email": "user100@example.com",
        "password_hash": "hash100",
        "role_id": 2,
        "profile_picture": "user100.jpg",
        "created_at": "2023-06-24T04:27:53",
        "updated_at": "2024-02-22T14:13:41"
    },
    {
        "id": 101,
        "name": "User 101",
        "email": "user101@example.com",
        "password_hash": "hash101",
        "role_id": 2,
        "profile_picture": "user101.jpg",
        "created_at": "2023-04-06T22:35:33",
        "updated_at": "2024-07-13T06:36:13"
    },
    {
        "id": 102,
        "name": "User 102",
        "email": "user102@example.com",
        "password_hash": "hash102",
        "role_id": 2,
        "profile_picture": "user102.jpg",
        "created_at": "2023-01-14T09:54:51",
        "updated_at": "2024-09-23T02:57:06"
    },
    {
        "id": 103,
        "name": "User 103",
        "email": "user103@example.com",
        "password_hash": "hash103",
        "role_id": 2,
        "profile_picture": "user103.jpg",
        "created_at": "2023-03-07T11:22:01",
        "updated_at": "2024-01-29T18:57:59"
    },
    {
        "id": 104,
        "name": "User 104",
        "email": "user104@example.com",
        "password_hash": "hash104",
        "role_id": 2,
        "profile_picture": "user104.jpg",
        "created_at": "2023-01-02T20:56:54",
        "updated_at": "2023-02-04T08:26:22"
    },
    {
        "id": 105,
        "name": "User 105",
        "email": "user105@example.com",
        "password_hash": "hash105",
        "role_id": 2,
        "profile_picture": "user105.jpg",
        "created_at": "2024-11-01T04:29:09",
        "updated_at": "2023-07-06T12:11:47"
    },
    {
        "id": 106,
        "name": "User 106",
        "email": "user106@example.com",
        "password_hash": "hash106",
        "role_id": 2,
        "profile_picture": "user106.jpg",
        "created_at": "2023-06-20T03:40:28",
        "updated_at": "2024-12-25T10:50:24"
    },
    {
        "id": 107,
        "name": "User 107",
        "email": "user107@example.com",
        "password_hash": "hash107",
        "role_id": 2,
        "profile_picture": "user107.jpg",
        "created_at": "2023-08-02T17:23:47",
        "updated_at": "2023-12-18T22:16:53"
    },
    {
        "id": 108,
        "name": "User 108",
        "email": "user108@example.com",
        "password_hash": "hash108",
        "role_id": 2,
        "profile_picture": "user108.jpg",
        "created_at": "2024-01-26T08:57:36",
        "updated_at": "2023-02-04T23:17:42"
    },
    {
        "id": 109,
        "name": "User 109",
        "email": "user109@example.com",
        "password_hash": "hash109",
        "role_id": 2,
        "profile_picture": "user109.jpg",
        "created_at": "2023-12-28T09:59:01",
        "updated_at": "2023-01-31T10:12:17"
    },
    {
        "id": 110,
        "name": "User 110",
        "email": "user110@example.com",
        "password_hash": "hash110",
        "role_id": 2,
        "profile_picture": "user110.jpg",
        "created_at": "2024-09-01T03:01:41",
        "updated_at": "2023-08-26T08:35:09"
    },
    {
        "id": 111,
        "name": "User 111",
        "email": "user111@example.com",
        "password_hash": "hash111",
        "role_id": 2,
        "profile_picture": "user111.jpg",
        "created_at": "2024-04-29T03:19:15",
        "updated_at": "2024-04-12T15:11:20"
    },
    {
        "id": 112,
        "name": "User 112",
        "email": "user112@example.com",
        "password_hash": "hash112",
        "role_id": 2,
        "profile_picture": "user112.jpg",
        "created_at": "2024-09-08T23:51:58",
        "updated_at": "2023-07-21T00:38:25"
    },
    {
        "id": 113,
        "name": "User 113",
        "email": "user113@example.com",
        "password_hash": "hash113",
        "role_id": 2,
        "profile_picture": "user113.jpg",
        "created_at": "2023-03-01T13:26:05",
        "updated_at": "2024-04-13T06:14:39"
    },
    {
        "id": 114,
        "name": "User 114",
        "email": "user114@example.com",
        "password_hash": "hash114",
        "role_id": 2,
        "profile_picture": "user114.jpg",
        "created_at": "2023-04-25T21:18:51",
        "updated_at": "2025-01-28T15:49:06"
    },
    {
        "id": 115,
        "name": "User 115",
        "email": "user115@example.com",
        "password_hash": "hash115",
        "role_id": 2,
        "profile_picture": "user115.jpg",
        "created_at": "2024-07-30T03:35:53",
        "updated_at": "2023-07-13T00:28:43"
    },
    {
        "id": 116,
        "name": "User 116",
        "email": "user116@example.com",
        "password_hash": "hash116",
        "role_id": 2,
        "profile_picture": "user116.jpg",
        "created_at": "2024-06-02T03:54:02",
        "updated_at": "2023-10-21T18:55:37"
    },
    {
        "id": 117,
        "name": "User 117",
        "email": "user117@example.com",
        "password_hash": "hash117",
        "role_id": 2,
        "profile_picture": "user117.jpg",
        "created_at": "2023-06-14T22:44:19",
        "updated_at": "2024-01-10T12:50:31"
    },
    {
        "id": 118,
        "name": "User 118",
        "email": "user118@example.com",
        "password_hash": "hash118",
        "role_id": 2,
        "profile_picture": "user118.jpg",
        "created_at": "2024-01-29T16:15:21",
        "updated_at": "2024-12-05T05:34:44"
    },
    {
        "id": 119,
        "name": "User 119",
        "email": "user119@example.com",
        "password_hash": "hash119",
        "role_id": 2,
        "profile_picture": "user119.jpg",
        "created_at": "2023-04-22T01:13:50",
        "updated_at": "2023-04-26T09:51:54"
    },
    {
        "id": 120,
        "name": "User 120",
        "email": "user120@example.com",
        "password_hash": "hash120",
        "role_id": 2,
        "profile_picture": "user120.jpg",
        "created_at": "2023-07-11T05:39:58",
        "updated_at": "2024-11-27T17:19:48"
    },
    {
        "id": 121,
        "name": "User 121",
        "email": "user121@example.com",
        "password_hash": "hash121",
        "role_id": 2,
        "profile_picture": "user121.jpg",
        "created_at": "2023-09-17T15:35:57",
        "updated_at": "2024-01-04T03:41:01"
    },
    {
        "id": 122,
        "name": "User 122",
        "email": "user122@example.com",
        "password_hash": "hash122",
        "role_id": 2,
        "profile_picture": "user122.jpg",
        "created_at": "2024-08-26T09:02:19",
        "updated_at": "2023-02-25T08:31:03"
    },
    {
        "id": 123,
        "name": "User 123",
        "email": "user123@example.com",
        "password_hash": "hash123",
        "role_id": 2,
        "profile_picture": "user123.jpg",
        "created_at": "2024-06-09T10:26:23",
        "updated_at": "2024-05-15T04:45:03"
    },
    {
        "id": 124,
        "name": "User 124",
        "email": "user124@example.com",
        "password_hash": "hash124",
        "role_id": 2,
        "profile_picture": "user124.jpg",
        "created_at": "2024-04-14T08:40:44",
        "updated_at": "2024-11-22T11:04:15"
    },
    {
        "id": 125,
        "name": "User 125",
        "email": "user125@example.com",
        "password_hash": "hash125",
        "role_id": 2,
        "profile_picture": "user125.jpg",
        "created_at": "2023-04-06T02:48:54",
        "updated_at": "2023-04-20T14:50:13"
    },
    {
        "id": 126,
        "name": "User 126",
        "email": "user126@example.com",
        "password_hash": "hash126",
        "role_id": 2,
        "profile_picture": "user126.jpg",
        "created_at": "2023-05-08T12:30:43",
        "updated_at": "2023-05-19T09:08:16"
    },
    {
        "id": 127,
        "name": "User 127",
        "email": "user127@example.com",
        "password_hash": "hash127",
        "role_id": 2,
        "profile_picture": "user127.jpg",
        "created_at": "2024-10-10T09:20:59",
        "updated_at": "2024-02-22T03:14:33"
    },
    {
        "id": 128,
        "name": "User 128",
        "email": "user128@example.com",
        "password_hash": "hash128",
        "role_id": 2,
        "profile_picture": "user128.jpg",
        "created_at": "2023-10-07T08:00:07",
        "updated_at": "2024-01-21T10:19:30"
    },
    {
        "id": 129,
        "name": "User 129",
        "email": "user129@example.com",
        "password_hash": "hash129",
        "role_id": 2,
        "profile_picture": "user129.jpg",
        "created_at": "2024-07-20T06:35:33",
        "updated_at": "2024-12-26T10:38:55"
    },
    {
        "id": 130,
        "name": "User 130",
        "email": "user130@example.com",
        "password_hash": "hash130",
        "role_id": 2,
        "profile_picture": "user130.jpg",
        "created_at": "2024-04-17T19:01:11",
        "updated_at": "2024-03-26T04:48:38"
    },
    {
        "id": 131,
        "name": "User 131",
        "email": "user131@example.com",
        "password_hash": "hash131",
        "role_id": 2,
        "profile_picture": "user131.jpg",
        "created_at": "2024-04-09T17:20:34",
        "updated_at": "2023-02-22T13:30:53"
    },
    {
        "id": 132,
        "name": "User 132",
        "email": "user132@example.com",
        "password_hash": "hash132",
        "role_id": 2,
        "profile_picture": "user132.jpg",
        "created_at": "2025-01-08T06:30:53",
        "updated_at": "2023-04-19T14:49:14"
    },
    {
        "id": 133,
        "name": "User 133",
        "email": "user133@example.com",
        "password_hash": "hash133",
        "role_id": 2,
        "profile_picture": "user133.jpg",
        "created_at": "2023-06-19T02:33:36",
        "updated_at": "2024-03-30T17:46:28"
    },
    {
        "id": 134,
        "name": "User 134",
        "email": "user134@example.com",
        "password_hash": "hash134",
        "role_id": 2,
        "profile_picture": "user134.jpg",
        "created_at": "2024-03-02T04:58:17",
        "updated_at": "2024-11-23T10:24:48"
    },
    {
        "id": 135,
        "name": "User 135",
        "email": "user135@example.com",
        "password_hash": "hash135",
        "role_id": 2,
        "profile_picture": "user135.jpg",
        "created_at": "2024-03-14T03:06:26",
        "updated_at": "2023-04-08T17:14:16"
    },
    {
        "id": 136,
        "name": "User 136",
        "email": "user136@example.com",
        "password_hash": "hash136",
        "role_id": 2,
        "profile_picture": "user136.jpg",
        "created_at": "2025-01-19T13:36:57",
        "updated_at": "2024-11-09T22:36:00"
    },
    {
        "id": 137,
        "name": "User 137",
        "email": "user137@example.com",
        "password_hash": "hash137",
        "role_id": 2,
        "profile_picture": "user137.jpg",
        "created_at": "2024-12-01T15:29:13",
        "updated_at": "2024-04-01T04:54:22"
    },
    {
        "id": 138,
        "name": "User 138",
        "email": "user138@example.com",
        "password_hash": "hash138",
        "role_id": 2,
        "profile_picture": "user138.jpg",
        "created_at": "2025-02-02T18:59:39",
        "updated_at": "2024-01-02T08:00:57"
    },
    {
        "id": 139,
        "name": "User 139",
        "email": "user139@example.com",
        "password_hash": "hash139",
        "role_id": 2,
        "profile_picture": "user139.jpg",
        "created_at": "2023-12-21T18:04:05",
        "updated_at": "2024-07-15T11:26:01"
    },
    {
        "id": 140,
        "name": "User 140",
        "email": "user140@example.com",
        "password_hash": "hash140",
        "role_id": 2,
        "profile_picture": "user140.jpg",
        "created_at": "2024-12-15T08:24:07",
        "updated_at": "2024-04-23T14:34:15"
    },
    {
        "id": 141,
        "name": "User 141",
        "email": "user141@example.com",
        "password_hash": "hash141",
        "role_id": 2,
        "profile_picture": "user141.jpg",
        "created_at": "2023-04-19T17:39:33",
        "updated_at": "2024-06-01T16:31:37"
    },
    {
        "id": 142,
        "name": "User 142",
        "email": "user142@example.com",
        "password_hash": "hash142",
        "role_id": 2,
        "profile_picture": "user142.jpg",
        "created_at": "2024-05-05T19:16:43",
        "updated_at": "2024-09-29T04:18:14"
    },
    {
        "id": 143,
        "name": "User 143",
        "email": "user143@example.com",
        "password_hash": "hash143",
        "role_id": 2,
        "profile_picture": "user143.jpg",
        "created_at": "2023-11-11T20:46:23",
        "updated_at": "2023-05-14T08:37:09"
    },
    {
        "id": 144,
        "name": "User 144",
        "email": "user144@example.com",
        "password_hash": "hash144",
        "role_id": 2,
        "profile_picture": "user144.jpg",
        "created_at": "2024-10-07T04:59:09",
        "updated_at": "2024-11-21T04:36:33"
    },
    {
        "id": 145,
        "name": "User 145",
        "email": "user145@example.com",
        "password_hash": "hash145",
        "role_id": 2,
        "profile_picture": "user145.jpg",
        "created_at": "2024-10-04T05:11:27",
        "updated_at": "2025-01-16T19:13:30"
    },
    {
        "id": 146,
        "name": "User 146",
        "email": "user146@example.com",
        "password_hash": "hash146",
        "role_id": 2,
        "profile_picture": "user146.jpg",
        "created_at": "2023-04-14T20:57:34",
        "updated_at": "2023-01-07T07:48:41"
    },
    {
        "id": 147,
        "name": "User 147",
        "email": "user147@example.com",
        "password_hash": "hash147",
        "role_id": 2,
        "profile_picture": "user147.jpg",
        "created_at": "2024-11-07T08:51:26",
        "updated_at": "2023-10-03T00:18:57"
    },
    {
        "id": 148,
        "name": "User 148",
        "email": "user148@example.com",
        "password_hash": "hash148",
        "role_id": 2,
        "profile_picture": "user148.jpg",
        "created_at": "2024-04-20T19:22:11",
        "updated_at": "2025-02-17T14:14:30"
    },
    {
        "id": 149,
        "name": "User 149",
        "email": "user149@example.com",
        "password_hash": "hash149",
        "role_id": 2,
        "profile_picture": "user149.jpg",
        "created_at": "2023-07-03T19:46:19",
        "updated_at": "2024-07-23T22:16:50"
    },
    {
        "id": 150,
        "name": "User 150",
        "email": "user150@example.com",
        "password_hash": "hash150",
        "role_id": 2,
        "profile_picture": "user150.jpg",
        "created_at": "2023-06-28T20:10:34",
        "updated_at": "2024-08-25T05:34:17"
    },
    {
        "id": 151,
        "name": "User 151",
        "email": "user151@example.com",
        "password_hash": "hash151",
        "role_id": 2,
        "profile_picture": "user151.jpg",
        "created_at": "2023-07-13T21:04:05",
        "updated_at": "2023-06-03T04:04:06"
    },
    {
        "id": 152,
        "name": "User 152",
        "email": "user152@example.com",
        "password_hash": "hash152",
        "role_id": 2,
        "profile_picture": "user152.jpg",
        "created_at": "2023-09-08T21:11:09",
        "updated_at": "2024-04-05T09:12:19"
    },
    {
        "id": 153,
        "name": "User 153",
        "email": "user153@example.com",
        "password_hash": "hash153",
        "role_id": 2,
        "profile_picture": "user153.jpg",
        "created_at": "2024-03-24T06:31:15",
        "updated_at": "2024-03-30T15:34:01"
    },
    {
        "id": 154,
        "name": "User 154",
        "email": "user154@example.com",
        "password_hash": "hash154",
        "role_id": 2,
        "profile_picture": "user154.jpg",
        "created_at": "2024-01-25T01:06:55",
        "updated_at": "2023-06-26T04:02:04"
    },
    {
        "id": 155,
        "name": "User 155",
        "email": "user155@example.com",
        "password_hash": "hash155",
        "role_id": 2,
        "profile_picture": "user155.jpg",
        "created_at": "2023-03-15T15:44:40",
        "updated_at": "2024-08-21T01:48:31"
    },
    {
        "id": 156,
        "name": "User 156",
        "email": "user156@example.com",
        "password_hash": "hash156",
        "role_id": 2,
        "profile_picture": "user156.jpg",
        "created_at": "2023-07-12T02:04:20",
        "updated_at": "2023-09-22T05:24:12"
    },
    {
        "id": 157,
        "name": "User 157",
        "email": "user157@example.com",
        "password_hash": "hash157",
        "role_id": 2,
        "profile_picture": "user157.jpg",
        "created_at": "2023-11-22T07:26:41",
        "updated_at": "2023-03-09T07:07:22"
    },
    {
        "id": 158,
        "name": "User 158",
        "email": "user158@example.com",
        "password_hash": "hash158",
        "role_id": 2,
        "profile_picture": "user158.jpg",
        "created_at": "2023-09-28T13:58:35",
        "updated_at": "2023-12-03T13:48:37"
    },
    {
        "id": 159,
        "name": "User 159",
        "email": "user159@example.com",
        "password_hash": "hash159",
        "role_id": 2,
        "profile_picture": "user159.jpg",
        "created_at": "2023-11-19T17:16:55",
        "updated_at": "2023-06-30T06:07:07"
    },
    {
        "id": 160,
        "name": "User 160",
        "email": "user160@example.com",
        "password_hash": "hash160",
        "role_id": 2,
        "profile_picture": "user160.jpg",
        "created_at": "2024-12-15T03:54:47",
        "updated_at": "2023-07-07T01:12:04"
    },
    {
        "id": 161,
        "name": "User 161",
        "email": "user161@example.com",
        "password_hash": "hash161",
        "role_id": 2,
        "profile_picture": "user161.jpg",
        "created_at": "2023-10-14T08:31:54",
        "updated_at": "2024-12-22T03:56:45"
    },
    {
        "id": 162,
        "name": "User 162",
        "email": "user162@example.com",
        "password_hash": "hash162",
        "role_id": 2,
        "profile_picture": "user162.jpg",
        "created_at": "2024-09-30T04:01:50",
        "updated_at": "2023-04-23T23:21:40"
    },
    {
        "id": 163,
        "name": "User 163",
        "email": "user163@example.com",
        "password_hash": "hash163",
        "role_id": 2,
        "profile_picture": "user163.jpg",
        "created_at": "2023-12-24T22:12:42",
        "updated_at": "2024-07-21T12:43:33"
    },
    {
        "id": 164,
        "name": "User 164",
        "email": "user164@example.com",
        "password_hash": "hash164",
        "role_id": 2,
        "profile_picture": "user164.jpg",
        "created_at": "2023-06-03T06:11:05",
        "updated_at": "2025-01-10T22:06:19"
    },
    {
        "id": 165,
        "name": "User 165",
        "email": "user165@example.com",
        "password_hash": "hash165",
        "role_id": 2,
        "profile_picture": "user165.jpg",
        "created_at": "2023-07-19T06:16:31",
        "updated_at": "2023-09-16T13:44:55"
    },
    {
        "id": 166,
        "name": "User 166",
        "email": "user166@example.com",
        "password_hash": "hash166",
        "role_id": 2,
        "profile_picture": "user166.jpg",
        "created_at": "2024-06-17T15:28:16",
        "updated_at": "2024-12-03T02:10:13"
    },
    {
        "id": 167,
        "name": "User 167",
        "email": "user167@example.com",
        "password_hash": "hash167",
        "role_id": 2,
        "profile_picture": "user167.jpg",
        "created_at": "2023-07-22T06:53:05",
        "updated_at": "2024-11-13T16:30:27"
    },
    {
        "id": 168,
        "name": "User 168",
        "email": "user168@example.com",
        "password_hash": "hash168",
        "role_id": 2,
        "profile_picture": "user168.jpg",
        "created_at": "2024-09-24T15:40:08",
        "updated_at": "2023-08-01T07:18:25"
    },
    {
        "id": 169,
        "name": "User 169",
        "email": "user169@example.com",
        "password_hash": "hash169",
        "role_id": 2,
        "profile_picture": "user169.jpg",
        "created_at": "2023-10-21T00:18:01",
        "updated_at": "2024-06-05T13:01:11"
    },
    {
        "id": 170,
        "name": "User 170",
        "email": "user170@example.com",
        "password_hash": "hash170",
        "role_id": 2,
        "profile_picture": "user170.jpg",
        "created_at": "2024-05-17T19:13:42",
        "updated_at": "2024-10-24T19:00:07"
    },
    {
        "id": 171,
        "name": "User 171",
        "email": "user171@example.com",
        "password_hash": "hash171",
        "role_id": 2,
        "profile_picture": "user171.jpg",
        "created_at": "2025-02-12T01:18:39",
        "updated_at": "2023-12-28T07:24:56"
    },
    {
        "id": 172,
        "name": "User 172",
        "email": "user172@example.com",
        "password_hash": "hash172",
        "role_id": 2,
        "profile_picture": "user172.jpg",
        "created_at": "2025-02-11T03:11:48",
        "updated_at": "2024-09-08T00:49:19"
    },
    {
        "id": 173,
        "name": "User 173",
        "email": "user173@example.com",
        "password_hash": "hash173",
        "role_id": 2,
        "profile_picture": "user173.jpg",
        "created_at": "2024-02-08T07:58:52",
        "updated_at": "2024-11-19T17:07:17"
    },
    {
        "id": 174,
        "name": "User 174",
        "email": "user174@example.com",
        "password_hash": "hash174",
        "role_id": 2,
        "profile_picture": "user174.jpg",
        "created_at": "2023-03-12T17:21:12",
        "updated_at": "2023-12-11T12:48:41"
    },
    {
        "id": 175,
        "name": "User 175",
        "email": "user175@example.com",
        "password_hash": "hash175",
        "role_id": 2,
        "profile_picture": "user175.jpg",
        "created_at": "2024-11-04T23:49:28",
        "updated_at": "2024-10-25T09:27:49"
    },
    {
        "id": 176,
        "name": "User 176",
        "email": "user176@example.com",
        "password_hash": "hash176",
        "role_id": 2,
        "profile_picture": "user176.jpg",
        "created_at": "2025-02-14T09:26:12",
        "updated_at": "2023-05-21T03:07:46"
    },
    {
        "id": 177,
        "name": "User 177",
        "email": "user177@example.com",
        "password_hash": "hash177",
        "role_id": 2,
        "profile_picture": "user177.jpg",
        "created_at": "2024-10-25T02:05:38",
        "updated_at": "2024-07-09T16:00:04"
    },
    {
        "id": 178,
        "name": "User 178",
        "email": "user178@example.com",
        "password_hash": "hash178",
        "role_id": 2,
        "profile_picture": "user178.jpg",
        "created_at": "2023-08-29T01:20:55",
        "updated_at": "2023-10-02T22:39:53"
    },
    {
        "id": 179,
        "name": "User 179",
        "email": "user179@example.com",
        "password_hash": "hash179",
        "role_id": 2,
        "profile_picture": "user179.jpg",
        "created_at": "2024-08-25T14:05:12",
        "updated_at": "2023-12-19T01:54:29"
    },
    {
        "id": 180,
        "name": "User 180",
        "email": "user180@example.com",
        "password_hash": "hash180",
        "role_id": 2,
        "profile_picture": "user180.jpg",
        "created_at": "2023-07-19T13:18:44",
        "updated_at": "2024-05-02T06:16:17"
    },
    {
        "id": 181,
        "name": "User 181",
        "email": "user181@example.com",
        "password_hash": "hash181",
        "role_id": 2,
        "profile_picture": "user181.jpg",
        "created_at": "2024-02-12T17:14:17",
        "updated_at": "2023-05-22T16:15:34"
    },
    {
        "id": 182,
        "name": "User 182",
        "email": "user182@example.com",
        "password_hash": "hash182",
        "role_id": 2,
        "profile_picture": "user182.jpg",
        "created_at": "2023-04-26T15:12:49",
        "updated_at": "2025-01-03T23:45:42"
    },
    {
        "id": 183,
        "name": "User 183",
        "email": "user183@example.com",
        "password_hash": "hash183",
        "role_id": 2,
        "profile_picture": "user183.jpg",
        "created_at": "2024-05-28T00:09:23",
        "updated_at": "2023-04-02T17:51:04"
    },
    {
        "id": 184,
        "name": "User 184",
        "email": "user184@example.com",
        "password_hash": "hash184",
        "role_id": 2,
        "profile_picture": "user184.jpg",
        "created_at": "2024-07-26T06:09:58",
        "updated_at": "2025-01-19T20:43:53"
    },
    {
        "id": 185,
        "name": "User 185",
        "email": "user185@example.com",
        "password_hash": "hash185",
        "role_id": 2,
        "profile_picture": "user185.jpg",
        "created_at": "2024-08-02T15:05:56",
        "updated_at": "2024-03-06T05:47:40"
    },
    {
        "id": 186,
        "name": "User 186",
        "email": "user186@example.com",
        "password_hash": "hash186",
        "role_id": 2,
        "profile_picture": "user186.jpg",
        "created_at": "2024-04-20T22:40:02",
        "updated_at": "2023-07-26T12:09:20"
    },
    {
        "id": 187,
        "name": "User 187",
        "email": "user187@example.com",
        "password_hash": "hash187",
        "role_id": 2,
        "profile_picture": "user187.jpg",
        "created_at": "2024-08-06T16:24:45",
        "updated_at": "2023-08-25T03:27:42"
    },
    {
        "id": 188,
        "name": "User 188",
        "email": "user188@example.com",
        "password_hash": "hash188",
        "role_id": 2,
        "profile_picture": "user188.jpg",
        "created_at": "2023-07-06T02:44:01",
        "updated_at": "2024-04-05T03:47:15"
    },
    {
        "id": 189,
        "name": "User 189",
        "email": "user189@example.com",
        "password_hash": "hash189",
        "role_id": 2,
        "profile_picture": "user189.jpg",
        "created_at": "2025-02-13T19:14:29",
        "updated_at": "2023-11-21T14:25:06"
    },
    {
        "id": 190,
        "name": "User 190",
        "email": "user190@example.com",
        "password_hash": "hash190",
        "role_id": 2,
        "profile_picture": "user190.jpg",
        "created_at": "2023-09-04T09:23:24",
        "updated_at": "2024-11-14T16:20:31"
    },
    {
        "id": 191,
        "name": "User 191",
        "email": "user191@example.com",
        "password_hash": "hash191",
        "role_id": 2,
        "profile_picture": "user191.jpg",
        "created_at": "2023-01-12T18:01:34",
        "updated_at": "2023-06-17T09:37:08"
    },
    {
        "id": 192,
        "name": "User 192",
        "email": "user192@example.com",
        "password_hash": "hash192",
        "role_id": 2,
        "profile_picture": "user192.jpg",
        "created_at": "2023-12-23T11:02:12",
        "updated_at": "2023-01-24T22:54:30"
    },
    {
        "id": 193,
        "name": "User 193",
        "email": "user193@example.com",
        "password_hash": "hash193",
        "role_id": 2,
        "profile_picture": "user193.jpg",
        "created_at": "2023-12-15T14:46:29",
        "updated_at": "2023-08-09T04:33:31"
    },
    {
        "id": 194,
        "name": "User 194",
        "email": "user194@example.com",
        "password_hash": "hash194",
        "role_id": 2,
        "profile_picture": "user194.jpg",
        "created_at": "2023-06-29T09:15:00",
        "updated_at": "2023-04-06T11:59:04"
    },
    {
        "id": 195,
        "name": "User 195",
        "email": "user195@example.com",
        "password_hash": "hash195",
        "role_id": 2,
        "profile_picture": "user195.jpg",
        "created_at": "2024-02-19T14:51:00",
        "updated_at": "2024-07-28T18:19:34"
    },
    {
        "id": 196,
        "name": "User 196",
        "email": "user196@example.com",
        "password_hash": "hash196",
        "role_id": 2,
        "profile_picture": "user196.jpg",
        "created_at": "2024-05-11T02:22:36",
        "updated_at": "2023-05-28T12:44:48"
    },
    {
        "id": 197,
        "name": "User 197",
        "email": "user197@example.com",
        "password_hash": "hash197",
        "role_id": 2,
        "profile_picture": "user197.jpg",
        "created_at": "2024-08-14T04:39:14",
        "updated_at": "2024-11-28T17:04:22"
    },
    {
        "id": 198,
        "name": "User 198",
        "email": "user198@example.com",
        "password_hash": "hash198",
        "role_id": 2,
        "profile_picture": "user198.jpg",
        "created_at": "2024-07-15T11:32:36",
        "updated_at": "2023-10-23T12:02:25"
    },
    {
        "id": 199,
        "name": "User 199",
        "email": "user199@example.com",
        "password_hash": "hash199",
        "role_id": 2,
        "profile_picture": "user199.jpg",
        "created_at": "2023-02-13T20:49:37",
        "updated_at": "2024-12-25T01:52:27"
    },
    {
        "id": 200,
        "name": "User 200",
        "email": "user200@example.com",
        "password_hash": "hash200",
        "role_id": 2,
        "profile_picture": "user200.jpg",
        "created_at": "2023-02-26T05:28:06",
        "updated_at": "2024-12-20T17:16:55"
    },
    {
        "id": 201,
        "name": "User 201",
        "email": "user201@example.com",
        "password_hash": "hash201",
        "role_id": 2,
        "profile_picture": "user201.jpg",
        "created_at": "2024-06-22T16:01:59",
        "updated_at": "2024-04-11T17:07:40"
    },
    {
        "id": 202,
        "name": "User 202",
        "email": "user202@example.com",
        "password_hash": "hash202",
        "role_id": 2,
        "profile_picture": "user202.jpg",
        "created_at": "2023-03-13T08:31:35",
        "updated_at": "2024-08-24T14:20:23"
    },
    {
        "id": 203,
        "name": "User 203",
        "email": "user203@example.com",
        "password_hash": "hash203",
        "role_id": 2,
        "profile_picture": "user203.jpg",
        "created_at": "2023-08-08T14:42:02",
        "updated_at": "2023-01-18T17:48:14"
    },
    {
        "id": 204,
        "name": "User 204",
        "email": "user204@example.com",
        "password_hash": "hash204",
        "role_id": 2,
        "profile_picture": "user204.jpg",
        "created_at": "2024-12-15T23:59:21",
        "updated_at": "2023-12-05T23:39:37"
    },
    {
        "id": 205,
        "name": "User 205",
        "email": "user205@example.com",
        "password_hash": "hash205",
        "role_id": 2,
        "profile_picture": "user205.jpg",
        "created_at": "2024-12-10T19:28:02",
        "updated_at": "2023-06-26T06:48:43"
    },
    {
        "id": 206,
        "name": "User 206",
        "email": "user206@example.com",
        "password_hash": "hash206",
        "role_id": 3,
        "profile_picture": "user206.jpg",
        "created_at": "2023-08-06T14:47:07",
        "updated_at": "2024-08-10T09:16:05"
    },
    {
        "id": 207,
        "name": "User 207",
        "email": "user207@example.com",
        "password_hash": "hash207",
        "role_id": 3,
        "profile_picture": "user207.jpg",
        "created_at": "2024-09-14T14:04:51",
        "updated_at": "2024-09-05T12:32:09"
    },
    {
        "id": 208,
        "name": "User 208",
        "email": "user208@example.com",
        "password_hash": "hash208",
        "role_id": 3,
        "profile_picture": "user208.jpg",
        "created_at": "2023-02-16T23:52:02",
        "updated_at": "2024-10-10T02:31:10"
    },
    {
        "id": 209,
        "name": "User 209",
        "email": "user209@example.com",
        "password_hash": "hash209",
        "role_id": 3,
        "profile_picture": "user209.jpg",
        "created_at": "2024-03-01T18:33:12",
        "updated_at": "2023-05-07T23:44:56"
    },
    {
        "id": 210,
        "name": "User 210",
        "email": "user210@example.com",
        "password_hash": "hash210",
        "role_id": 3,
        "profile_picture": "user210.jpg",
        "created_at": "2023-12-15T07:42:55",
        "updated_at": "2023-10-22T08:21:56"
    },
    {
        "id": 211,
        "name": "User 211",
        "email": "user211@example.com",
        "password_hash": "hash211",
        "role_id": 3,
        "profile_picture": "user211.jpg",
        "created_at": "2024-04-19T07:03:21",
        "updated_at": "2024-05-02T04:36:22"
    },
    {
        "id": 212,
        "name": "User 212",
        "email": "user212@example.com",
        "password_hash": "hash212",
        "role_id": 3,
        "profile_picture": "user212.jpg",
        "created_at": "2024-05-15T10:52:12",
        "updated_at": "2023-08-19T17:38:54"
    },
    {
        "id": 213,
        "name": "User 213",
        "email": "user213@example.com",
        "password_hash": "hash213",
        "role_id": 3,
        "profile_picture": "user213.jpg",
        "created_at": "2023-12-28T17:38:22",
        "updated_at": "2023-10-03T15:41:41"
    },
    {
        "id": 214,
        "name": "User 214",
        "email": "user214@example.com",
        "password_hash": "hash214",
        "role_id": 3,
        "profile_picture": "user214.jpg",
        "created_at": "2024-03-25T09:16:21",
        "updated_at": "2023-05-24T11:56:08"
    },
    {
        "id": 215,
        "name": "User 215",
        "email": "user215@example.com",
        "password_hash": "hash215",
        "role_id": 3,
        "profile_picture": "user215.jpg",
        "created_at": "2023-01-02T02:22:35",
        "updated_at": "2023-10-05T21:00:09"
    },
    {
        "id": 216,
        "name": "User 216",
        "email": "user216@example.com",
        "password_hash": "hash216",
        "role_id": 3,
        "profile_picture": "user216.jpg",
        "created_at": "2024-08-19T22:32:54",
        "updated_at": "2023-04-25T01:14:57"
    }
]